ansys/pyensight/core/__init__.py
ansys/pyensight/core/common.py
ansys/pyensight/core/deep_pixel_view.html
ansys/pyensight/core/dockerlauncher.py
ansys/pyensight/core/dvs.py
ansys/pyensight/core/enscontext.py
ansys/pyensight/core/enshell_grpc.py
ansys/pyensight/core/ensight_grpc.py
ansys/pyensight/core/ensobj.py
ansys/pyensight/core/launch_ensight.py
ansys/pyensight/core/launcher.py
ansys/pyensight/core/libuserd.py
ansys/pyensight/core/listobj.py
ansys/pyensight/core/locallauncher.py
ansys/pyensight/core/py.typed
ansys/pyensight/core/renderable.py
ansys/pyensight/core/session.py
ansys/pyensight/core/sgeo_poll.html
ansys/pyensight/core/utils/__init__.py
ansys/pyensight/core/utils/adr.py
ansys/pyensight/core/utils/dsg_server.py
ansys/pyensight/core/utils/export.py
ansys/pyensight/core/utils/omniverse.py
ansys/pyensight/core/utils/omniverse_cli.py
ansys/pyensight/core/utils/omniverse_dsg_server.py
ansys/pyensight/core/utils/omniverse_glb_server.py
ansys/pyensight/core/utils/parts.py
ansys/pyensight/core/utils/query.py
ansys/pyensight/core/utils/readers.py
ansys/pyensight/core/utils/support.py
ansys/pyensight/core/utils/variables.py
ansys/pyensight/core/utils/views.py
ansys/pyensight/core/utils/resources/Materials/000_sky.exr
ansys_pyensight_core-0.11.2.dist-info/licenses/LICENSE
ansys_pyensight_core-0.11.2.dist-info/WHEEL
ansys_pyensight_core-0.11.2.dist-info/METADATA
ansys_pyensight_core-0.11.2.dist-info/RECORD
