Metadata-Version: 2.4
Name: ansys-pyensight-core
Version: 0.11.2
Summary: A python wrapper for Ansys EnSight
Author-email: "ANSYS, Inc." <pyansys.core@ansys.com>
Maintainer-email: "ANSYS, Inc." <pyansys.core@ansys.com>
Requires-Python: >=3.10,<3.14
Classifier: Development Status :: 4 - Beta
Classifier: Intended Audience :: Science/Research
Classifier: Topic :: Scientific/Engineering :: Information Analysis
Classifier: License :: OSI Approved :: MIT License
Classifier: Operating System :: OS Independent
Classifier: Programming Language :: Python :: 3.10
Classifier: Programming Language :: Python :: 3.11
Classifier: Programming Language :: Python :: 3.12
Classifier: Programming Language :: Python :: 3.13
License-File: LICENSE
Requires-Dist: importlib-metadata>=4.0; python_version<='3.8'
Requires-Dist: ansys-api-pyensight==0.4.11
Requires-Dist: requests>=2.28.2
Requires-Dist: docker>=6.1.0
Requires-Dist: urllib3<3
Requires-Dist: numpy>=1.21.0,<3
Requires-Dist: Pillow>=9.3.0
Requires-Dist: pypng>=0.0.20
Requires-Dist: psutil>=5.9.2
Requires-Dist: usd-core==25.11; platform_machine != 'aarch64'
Requires-Dist: pygltflib>=1.16.2
Requires-Dist: grpcio<1.68.0
Requires-Dist: ansys-tools-common>=0.3.0
Requires-Dist: build>=0.10.0 ; extra == "dev"
Requires-Dist: bump2version>=1.0.1 ; extra == "dev"
Requires-Dist: ipdb>=0.9.4 ; extra == "dev"
Requires-Dist: dill>=0.3.5.1 ; extra == "dev"
Requires-Dist: pre-commit>=3.3.3 ; extra == "dev"
Requires-Dist: Sphinx==8.1.3 ; extra == "doc"
Requires-Dist: numpydoc==1.10.0 ; extra == "doc"
Requires-Dist: ansys-sphinx-theme==1.6.3 ; extra == "doc"
Requires-Dist: sphinx-copybutton==0.5.2 ; extra == "doc"
Requires-Dist: sphinx-gallery==0.20.0 ; extra == "doc"
Requires-Dist: sphinxcontrib-mermaid==1.2.3 ; extra == "doc"
Requires-Dist: docker>=6.1.0 ; extra == "doc"
Requires-Dist: matplotlib==3.10.1 ; extra == "doc"
Requires-Dist: requests>=2.28.2 ; extra == "doc"
Requires-Dist: sphinxcontrib.jquery==4.1 ; extra == "doc"
Requires-Dist: sphinxcontrib-openapi==0.8.4 ; extra == "doc"
Requires-Dist: coverage-badge==1.1.2 ; extra == "doc"
Requires-Dist: sphinxcontrib-video==0.4.1 ; extra == "doc"
Requires-Dist: usd-core>=25.8 ; extra == "doc"
Requires-Dist: pygltflib>=1.16.2 ; extra == "doc"
Requires-Dist: pytest==9.0.1 ; extra == "tests"
Requires-Dist: pytest-cov==5.0.0 ; extra == "tests"
Requires-Dist: dill>=0.3.5.1 ; extra == "tests"
Requires-Dist: pytest-mock==3.15.1 ; extra == "tests"
Requires-Dist: urllib3<3.0.0 ; extra == "tests"
Requires-Dist: requests>=2.28.2 ; extra == "tests"
Requires-Dist: docker>=6.1.0 ; extra == "tests"
Requires-Dist: pytest-xdist==3.8.0 ; extra == "tests"
Requires-Dist: pytest-rerunfailures>=14,<17 ; extra == "tests"
Project-URL: Changelog, https://github.com/ansys/pyensight/blob/main/CHANGELOG.rst
Project-URL: Documentation, https://ensight.docs.pyansys.com/
Project-URL: Homepage, https://github.com/ansys/pyensight
Project-URL: Source, https://github.com/ansys/pyensight
Project-URL: Tracker, https://github.com/ansys/pyensight/issues
Provides-Extra: dev
Provides-Extra: doc
Provides-Extra: tests
